README.md
setup.cfg
setup.py
CloudConformity/APIKey.py
CloudConformity/Accounts.py
CloudConformity/Checks.py
CloudConformity/Events.py
CloudConformity/ExternalID.py
CloudConformity/Profiles.py
CloudConformity/ReportConfigs.py
CloudConformity/Resources.py
CloudConformity/Rules.py
CloudConformity/Settings.py
CloudConformity/TemplateScanner.py
CloudConformity/Users.py
CloudConformity/__init__.py
CloudConformity/__version__.py
CloudConformity/config.py
CloudConformity/connect.py
cc_sdk_mini.egg-info/PKG-INFO
cc_sdk_mini.egg-info/SOURCES.txt
cc_sdk_mini.egg-info/dependency_links.txt
cc_sdk_mini.egg-info/requires.txt
cc_sdk_mini.egg-info/top_level.txt